{"Shared":[],"Country Music":[{"title":"Song44","artist":"Song44(Artist)","album":"Song44(Album)","mp3":".\/MusicFiles\/44.mp3"},{"title":"43Title","artist":"43Artist","album":"43Album","mp3":".\/MusicFiles\/43.mp3"}],"Random Songs":[{"title":"Cold as hell","artist":"DZA","album":"Five-Finger Discount","mp3":".\/MusicFiles\/20.mp3"},{"title":"Morning light","artist":"Akamushi","album":"Poo Pop","mp3":".\/MusicFiles\/27.mp3"},{"title":"Permintaan Hati","artist":"Letto","album":"Don't Make Me Sad","mp3":".\/MusicFiles\/33.mp3"},{"title":"Darlin' Corey","artist":"Feral Mouth","album":"Olympus Chympus","mp3":".\/MusicFiles\/36.mp3"}]}